ddapi/__init__.py
ddapi/_api.py
ddapi/enum.py
ddapi/types.py
ddapi/util.py
ddapi/api/__init__.py
ddapi/api/ddnet.py
ddapi/api/ddstats.py
ddapi/api/status.py
ddapi/cache/__init__.py
ddapi/cache/base.py
ddapi/cache/empty.py
ddapi/cache/memory.py
ddapi/scheme/__init__.py
ddapi/scheme/ddnet.py
ddapi/scheme/ddstats_tw.py
ddapi/scheme/status_tw.py
ddapi-0.14.3.dist-info/licenses/LICENSE
ddapi-0.14.3.dist-info/METADATA
ddapi-0.14.3.dist-info/WHEEL
ddapi-0.14.3.dist-info/top_level.txt
ddapi-0.14.3.dist-info/RECORD
