Metadata-Version: 2.4
Name: ddapi
Version: 0.14.3
Summary: DDnet api
Home-page: https://github.com/ByFox213/ddapi
Author: ByFox
License: MIT
Project-URL: Github, https://github.com/ByFox213/ddapi
Requires-Python: >=3.10
License-File: LICENSE
Dynamic: author
Dynamic: description
Dynamic: description-content-type
Dynamic: home-page
Dynamic: license
Dynamic: license-file
Dynamic: project-url
Dynamic: requires-python
Dynamic: summary
